nj_image_searcher/__init__.py
nj_image_searcher/cli.py
nj_image_searcher/core.py
nj_image_searcher-0.1.1.dist-info/LICENSE
nj_image_searcher-0.1.1.dist-info/METADATA
nj_image_searcher-0.1.1.dist-info/WHEEL
nj_image_searcher-0.1.1.dist-info/entry_points.txt
nj_image_searcher-0.1.1.dist-info/RECORD
